boatman/ansi.py
boatman/appinfo.py
boatman/AUTHORS.txt
boatman/boatman.py
boatman/ChangeLog.txt
boatman/LICENSE.txt
boatman/localization.py
boatman/README.txt
boatman/utils.py
boatman/__init__.py
boatman/doc/.buildinfo
boatman/doc/authors.html
boatman/doc/boatman.pdf
boatman/doc/changelog.html
boatman/doc/genindex.html
boatman/doc/index.html
boatman/doc/license.html
boatman/doc/objects.inv
boatman/doc/py-modindex.html
boatman/doc/readme.html
boatman/doc/reference.html
boatman/doc/search.html
boatman/doc/searchindex.js
boatman/doc/_modules/ansi.html
boatman/doc/_modules/boatman.html
boatman/doc/_modules/index.html
boatman/doc/_modules/localization.html
boatman/doc/_modules/utils.html
boatman/doc/_sources/authors.txt
boatman/doc/_sources/changelog.txt
boatman/doc/_sources/index.txt
boatman/doc/_sources/license.txt
boatman/doc/_sources/readme.txt
boatman/doc/_sources/reference.txt
boatman/doc/_static/ajax-loader.gif
boatman/doc/_static/alabaster.css
boatman/doc/_static/basic.css
boatman/doc/_static/comment-bright.png
boatman/doc/_static/comment-close.png
boatman/doc/_static/comment.png
boatman/doc/_static/doctools.js
boatman/doc/_static/down-pressed.png
boatman/doc/_static/down.png
boatman/doc/_static/file.png
boatman/doc/_static/jquery-1.11.1.js
boatman/doc/_static/jquery.js
boatman/doc/_static/minus.png
boatman/doc/_static/plus.png
boatman/doc/_static/pygments.css
boatman/doc/_static/searchtools.js
boatman/doc/_static/underscore-1.3.1.js
boatman/doc/_static/underscore.js
boatman/doc/_static/up-pressed.png
boatman/doc/_static/up.png
boatman/doc/_static/websupport.js
boatman-0.0.6.dist-info/DESCRIPTION.rst
boatman-0.0.6.dist-info/entry_points.txt
boatman-0.0.6.dist-info/METADATA
boatman-0.0.6.dist-info/metadata.json
boatman-0.0.6.dist-info/RECORD
boatman-0.0.6.dist-info/top_level.txt
boatman-0.0.6.dist-info/WHEEL
