Metadata-Version: 2.0
Name: boatman
Version: 0.0.6
Summary: A simple logic game.
Home-page: https://github.com/jcrmatos/boatman
Author: Joao Carlos Roseta Matos
Author-email: jcrmatos@gmail.com
License: GNU General Public License v2 or later (GPLv2+)
Keywords: b,o,a,t, ,m,a,n
Platform: UNKNOWN
Classifier: Development Status :: 4 - Beta
Classifier: Environment :: Console
Classifier: Intended Audience :: End Users/Desktop
Classifier: License :: OSI Approved :: GNU General Public License v2 or later (GPLv2+)
Classifier: Natural Language :: English
Classifier: Natural Language :: Portuguese
Classifier: Operating System :: OS Independent
Classifier: Programming Language :: Python
Classifier: Programming Language :: Python :: 2
Classifier: Programming Language :: Python :: 2.7
Classifier: Programming Language :: Python :: 3
Classifier: Programming Language :: Python :: 3.4
Classifier: Topic :: Games/Entertainment
Requires-Dist: colorama
Requires-Dist: future
